[
    {
        "name": "Speed Hub",
        "code": "loadstring(game:HttpGet('https://example.com/speed-hub.lua'))()"
    },
    {
        "name": "Infinite Yield",
        "code": "loadstring(game:HttpGet('https://example.com/infinite-yield.lua'))()"
    },
    {
        "name": "ESP (Open Source)",
        "code": "loadstring(game:HttpGet('https://pastebin.com/raw/iP5Swf9a'))()"
    },
    {
        "name": "Forsaken",
        "code": "-- key is: web\nloadstring(game:HttpGet(\"https://raw.githubusercontent.com/souyanen/Fsscripts/refs/heads/main/Forsaken\"))()"
    }
]
